qfsclient/__init__.py
trpc/__init__.py
qfsclient-0.0.1.dist-info/METADATA
qfsclient-0.0.1.dist-info/WHEEL
qfsclient-0.0.1.dist-info/entry_points.txt
qfsclient-0.0.1.dist-info/top_level.txt
qfsclient-0.0.1.dist-info/RECORD
