Metadata-Version: 2.1
Name: qfsclient
Version: 0.0.1
Summary: ddd
Home-page: https://www.google.com
Author: qfsclient
Author-email: testtt@google.com
License: UNKNOWN
Platform: UNKNOWN
